zeo_utils
