Metadata-Version: 2.1
Name: zeo-utils
Version: 0.0.2
Summary: Utilities for ZEO++
Home-page: https://github.com/zbc0315/zeo_utils
Author: zhang
Author-email: zhangbc0315@outlook.com
Classifier: Programming Language :: Python :: 3
Classifier: License :: OSI Approved :: MIT License
Classifier: Operating System :: OS Independent
Requires-Python: >=3.7
License-File: LICENSE
